nomad_neb_workflows/__init__.py
nomad_neb_workflows/schema_packages/__init__.py
nomad_neb_workflows/schema_packages/neb.py
nomad_neb_workflows-1.0.3.dist-info/licenses/LICENSE
nomad_neb_workflows-1.0.3.dist-info/METADATA
nomad_neb_workflows-1.0.3.dist-info/WHEEL
nomad_neb_workflows-1.0.3.dist-info/entry_points.txt
nomad_neb_workflows-1.0.3.dist-info/top_level.txt
nomad_neb_workflows-1.0.3.dist-info/RECORD
