Metadata-Version: 2.4
Name: nomad-neb-workflows
Version: 1.0.3
Summary: A NOMAD plugin containing the section definitions of a standard Nudged Elastic Band (NEB) workflow.
Author-email: Julia Schumann <julia.schumann@physik.hu-berlin.de>, Uday Gajera <uday.gajera@physik.hu-berlin.de>, "Jose M. Pizarro" <jose.pizarro@physik.hu-berlin.de>, Hampus Näsström <hampus.naesstroem@physik.hu-berlin.de>
Maintainer-email: Julia Schumann <julia.schumann@physik.hu-berlin.de>, Uday Gajera <uday.gajera@physik.hu-berlin.de>, Hampus Näsström <hampus.naesstroem@physik.hu-berlin.de>
License: 
Project-URL: Homepage, https://github.com/FAIRmat-NFDI/nomad-neb-workflows
Project-URL: Bug Tracker, https://github.com/FAIRmat-NFDI/nomad-neb-workflows/issues
Project-URL: Documentation, https://FAIRmat-NFDI.github.io/nomad-neb-workflows/
Keywords: NOMAD,NEB,materials-science,workflows
Classifier: Intended Audience :: Developers
Classifier: Operating System :: OS Independent
Classifier: Programming Language :: Python
Classifier: Programming Language :: Python :: 3.10
Classifier: Programming Language :: Python :: 3.11
Classifier: Programming Language :: Python :: 3.12
Classifier: License :: OSI Approved :: Apache Software License
Requires-Python: >=3.10
License-File: LICENSE
Requires-Dist: nomad-lab>=1.3.14
Requires-Dist: nomad-schema-plugin-simulation-workflow>=1.0.10
Provides-Extra: dev
Requires-Dist: mypy>=1.15; extra == "dev"
Requires-Dist: ruff; extra == "dev"
Requires-Dist: pytest; extra == "dev"
Requires-Dist: pytest-timeout; extra == "dev"
Requires-Dist: pytest-cov; extra == "dev"
Requires-Dist: structlog; extra == "dev"
Requires-Dist: lxml_html_clean>=0.1.0; extra == "dev"
Requires-Dist: nomad-parser-plugins-electronic>=1.0; extra == "dev"
Requires-Dist: nomad-parser-plugins-atomistic>=1.0; extra == "dev"
Requires-Dist: nomad-parser-plugins-workflow>=1.0; extra == "dev"
Requires-Dist: nomad-parser-plugins-database>=1.0; extra == "dev"
Requires-Dist: nomad-simulations>=0.3.2; extra == "dev"
Requires-Dist: nomad-schema-plugin-run>=1.0.1; extra == "dev"
Requires-Dist: nomad-normalizer-plugin-bandstructure>=1.0; extra == "dev"
Requires-Dist: nomad-normalizer-plugin-dos>=1.0; extra == "dev"
Requires-Dist: nomad-normalizer-plugin-soap>=1.0; extra == "dev"
Requires-Dist: nomad-normalizer-plugin-spectra>=1.0; extra == "dev"
Requires-Dist: nomad-normalizer-plugin-system>=1.0; extra == "dev"
Requires-Dist: nomad-normalizer-plugin-simulation-workflow>=1.0; extra == "dev"
Dynamic: license-file
